cds_trytond_account_payment_beanstream-4.6.0.dist-info/DESCRIPTION.rst
cds_trytond_account_payment_beanstream-4.6.0.dist-info/METADATA
cds_trytond_account_payment_beanstream-4.6.0.dist-info/RECORD
cds_trytond_account_payment_beanstream-4.6.0.dist-info/WHEEL
cds_trytond_account_payment_beanstream-4.6.0.dist-info/entry_points.txt
cds_trytond_account_payment_beanstream-4.6.0.dist-info/metadata.json
cds_trytond_account_payment_beanstream-4.6.0.dist-info/top_level.txt
trytond/modules/account_payment_beanstream/__init__.py
trytond/modules/account_payment_beanstream/party.py
trytond/modules/account_payment_beanstream/payment.py
trytond/modules/account_payment_beanstream/payment.xml
trytond/modules/account_payment_beanstream/tryton.cfg
trytond/modules/account_payment_beanstream/view/account_form.xml
trytond/modules/account_payment_beanstream/view/account_list.xml
trytond/modules/account_payment_beanstream/view/customer_form.xml
trytond/modules/account_payment_beanstream/view/customer_list.xml
trytond/modules/account_payment_beanstream/view/payment_form.xml
trytond/modules/account_payment_beanstream/view/payment_journal_form.xml
