Metadata-Version: 2.0
Name: cds-trytond-account-payment-beanstream
Version: 4.6.0
Summary: Tryton module for BeanStream payment
Home-page: https://src.coalesco.ca/tryton/modules/cds_trytond_account_payment_beanstream
Author: Tryton
Author-email: it@coalesco.ca
License: GPL-3
Download-URL: https://src.coalesco.ca/tryton/modules/cds_trytond_account_ca_gifi/archive/tip.zip
Keywords: tryton account payment beanstream
Platform: UNKNOWN
Classifier: Development Status :: 4 - Beta
Classifier: Environment :: Plugins
Classifier: Framework :: Tryton
Classifier: Intended Audience :: Developers
Classifier: Intended Audience :: Financial and Insurance Industry
Classifier: Intended Audience :: Legal Industry
Classifier: License :: OSI Approved :: GNU General Public License v3 or later (GPLv3+)
Classifier: Natural Language :: English
Classifier: Operating System :: OS Independent
Classifier: Programming Language :: Python :: 2.7
Classifier: Programming Language :: Python :: 3.3
Classifier: Programming Language :: Python :: 3.4
Classifier: Programming Language :: Python :: 3.5
Classifier: Programming Language :: Python :: Implementation :: CPython
Classifier: Programming Language :: Python :: Implementation :: PyPy
Classifier: Topic :: Office/Business
Classifier: Topic :: Office/Business :: Financial :: Accounting
Requires-Dist: beanstream
Requires-Dist: enum34
Requires-Dist: trytond-sale (<4.7,>=4.6)
Requires-Dist: trytond-account-payment (<4.7,>=4.6)
Requires-Dist: trytond (<4.7,>=4.6)
